Metadata-Version: 2.1
Name: odoo-addon-hr_employee_lastnames
Version: 16.0.1.0.2.4
Summary: Split Name in First Name, Father's Last Name and Mother's Last Name
Home-page: https://github.com/OCA/hr
Author: Vauxoo, Odoo Community Association (OCA)
Author-email: support@odoo-community.org
License: AGPL-3
Classifier: Programming Language :: Python
Classifier: Framework :: Odoo
Classifier: Framework :: Odoo :: 16.0
Classifier: License :: OSI Approved :: GNU Affero General Public License v3
Requires-Python: >=3.10
Requires-Dist: odoo-addon-hr-employee-firstname<16.1dev,>=16.0dev
Requires-Dist: odoo-addon-partner-second-lastname<16.1dev,>=16.0dev
Requires-Dist: odoo<16.1dev,>=16.0a
